Metadata-Version: 1.0
Name: opticalmaterialspy
Version: 0.2
Summary: Python library with optical material properties.
Home-page: https://github.com/jtambasco/opticalmaterialspy
Author: Jean-Luc Tambasco
Author-email: an.obscurity@gmail.com
License: MIT
Platform: UNKNOWN
